spyprot/Command.py
spyprot/EditPdbXyz.py
spyprot/__init__.py
spyprot/cddf_parser.py
spyprot/cif2Wanda.py
spyprot/common.py
spyprot/fetchAnnotations.py
spyprot/fetchChainInfo.py
spyprot/fetchPDBinfo.py
spyprot/idMapping.py
spyprot/ilbsm_database_downloader.py
spyprot/pdb2Wanda.py
spyprot/spyProt.py
spyprot-1.0.4.dist-info/METADATA
spyprot-1.0.4.dist-info/WHEEL
spyprot-1.0.4.dist-info/top_level.txt
spyprot-1.0.4.dist-info/RECORD
