Metadata-Version: 2.4
Name: spyprot
Version: 1.0.4
Summary: This package provides a set of tools for accessing protein databases and manipulating PDB/CIF files.
Home-page: https://github.com/ilbsm/spyProt
Author: INTERDISCIPLINARY LABORATORY of BIOLOGICAL SYSTEMS MODELLING, University of Warsaw, Warsaw, Poland
Author-email: bmjastrzebski@gmail.com, p.rubach@cent.uw.edu.pl
Classifier: Programming Language :: Python :: 3
Classifier: Programming Language :: Python :: 3.8
Classifier: Programming Language :: Python :: 3.9
Classifier: Programming Language :: Python :: 3.10
Classifier: Programming Language :: Python :: 3.11
Classifier: Programming Language :: Python :: 3.12
Classifier: Programming Language :: Python :: 3.13
Classifier: Programming Language :: Python :: 3.14
Classifier: License :: OSI Approved :: MIT License
Classifier: Operating System :: OS Independent
Requires-Python: >=3.6.0
Requires-Dist: tqdm>=4.31.1
Requires-Dist: lxml>=4.5.0
Requires-Dist: requests>=2.0.0
Requires-Dist: biopython>1.60
Requires-Dist: psutil>5.6.0
Requires-Dist: subprocess32>=3.5.0
Requires-Dist: wget>=3.0
Requires-Dist: pysolr>=3.9.0
Dynamic: author
Dynamic: author-email
Dynamic: classifier
Dynamic: description
Dynamic: description-content-type
Dynamic: home-page
Dynamic: requires-dist
Dynamic: requires-python
Dynamic: summary
